cirquit/__init__.py
cirquit/cirquit.py
cirquit/gates.py
cirquit/py.typed
cirquit/results.py
cirquit/simulator.py
cirquit/visualization.py
cirquit-1.1.0.dist-info/licenses/LICENSE
cirquit-1.1.0.dist-info/METADATA
cirquit-1.1.0.dist-info/WHEEL
cirquit-1.1.0.dist-info/entry_points.txt
cirquit-1.1.0.dist-info/top_level.txt
cirquit-1.1.0.dist-info/RECORD
