Metadata-Version: 2.4
Name: cirquit
Version: 1.1.0
Summary: Quantum circuits, simplified. A developer-first quantum computing platform.
Author-email: Cirquit Team <hello@cirquit.io>
Maintainer-email: Cirquit Team <hello@cirquit.io>
License: MIT
Project-URL: Homepage, https://cirquit.io
Project-URL: Documentation, https://docs.cirquit.io
Project-URL: Repository, https://github.com/cirquit/cirquit
Project-URL: Bug Tracker, https://github.com/cirquit/cirquit/issues
Project-URL: Discord, https://discord.gg/cirquit
Project-URL: Twitter, https://twitter.com/cirquit_io
Project-URL: Changelog, https://github.com/cirquit/cirquit/blob/main/CHANGELOG.md
Keywords: quantum,quantum-computing,quantum-circuits,qubits,quantum-algorithms,qaas
Classifier: Development Status :: 4 - Beta
Classifier: Intended Audience :: Developers
Classifier: Intended Audience :: Science/Research
Classifier: License :: OSI Approved :: MIT License
Classifier: Programming Language :: Python :: 3
Classifier: Programming Language :: Python :: 3.11
Classifier: Programming Language :: Python :: 3.12
Classifier: Topic :: Scientific/Engineering :: Physics
Classifier: Typing :: Typed
Requires-Python: >=3.11
License-File: LICENSE
Requires-Dist: numpy>=1.24.0
Requires-Dist: scipy>=1.10.0
Provides-Extra: dev
Requires-Dist: pytest>=7.4.0; extra == "dev"
Requires-Dist: pytest-cov>=4.1.0; extra == "dev"
Requires-Dist: pytest-asyncio>=0.21.0; extra == "dev"
Requires-Dist: black>=23.7.0; extra == "dev"
Requires-Dist: isort>=5.12.0; extra == "dev"
Requires-Dist: mypy>=1.5.0; extra == "dev"
Requires-Dist: pylint>=2.17.0; extra == "dev"
Requires-Dist: flake8>=6.1.0; extra == "dev"
Requires-Dist: pre-commit>=3.3.0; extra == "dev"
Provides-Extra: docs
Requires-Dist: sphinx>=7.0.0; extra == "docs"
Requires-Dist: sphinx-rtd-theme>=1.3.0; extra == "docs"
Requires-Dist: sphinx-autodoc-typehints>=1.24.0; extra == "docs"
Requires-Dist: myst-parser>=2.0.0; extra == "docs"
Provides-Extra: viz
Requires-Dist: matplotlib>=3.7.0; extra == "viz"
Requires-Dist: plotly>=5.15.0; extra == "viz"
Provides-Extra: performance
Requires-Dist: cupy-cuda11x>=12.0.0; extra == "performance"
Requires-Dist: numba>=0.57.0; extra == "performance"
Provides-Extra: cloud
Requires-Dist: requests>=2.31.0; extra == "cloud"
Requires-Dist: websockets>=11.0.0; extra == "cloud"
Requires-Dist: python-dotenv>=1.0.0; extra == "cloud"
Provides-Extra: all
Requires-Dist: cirquit[cloud,dev,docs,viz]; extra == "all"
Dynamic: license-file
